gravy/__init__.py
gravy/__main__.py
gravy/core/__init__.py
gravy/core/cfg.toml
gravy/tests/__init__.py
gravy/tests/test_gravy.py
gravy-1.0.15.dist-info/licenses/LICENSE.txt
gravy-1.0.15.dist-info/METADATA
gravy-1.0.15.dist-info/WHEEL
gravy-1.0.15.dist-info/top_level.txt
gravy-1.0.15.dist-info/RECORD
