Metadata-Version: 2.4
Name: gravy
Version: 1.0.15
Summary: This project calculates the GRAVY score of a amino acid sequence.
Author-email: Johannes <johannes.programming@gmail.com>
License: The MIT License (MIT)
Project-URL: Download, https://pypi.org/project/gravy/#files
Project-URL: Index, https://pypi.org/project/gravy/
Project-URL: Source, https://github.com/johannes-programming/gravy/
Project-URL: Website, https://gravy.johannes-programming.online/
Classifier: Development Status :: 5 - Production/Stable
Classifier: Intended Audience :: Science/Research
Classifier: License :: OSI Approved :: MIT License
Classifier: Natural Language :: English
Classifier: Operating System :: OS Independent
Classifier: Programming Language :: Python
Classifier: Programming Language :: Python :: 3
Classifier: Programming Language :: Python :: 3 :: Only
Classifier: Topic :: Scientific/Engineering :: Bio-Informatics
Classifier: Typing :: Typed
Requires-Python: >=3.11
License-File: LICENSE.txt
Requires-Dist: click>=8.2.1
Requires-Dist: preparse>=0.1.6
Dynamic: license-file
